{
  "type": "forge:conditional",
  "recipes": [
    {
      "conditions": [
        {
          "type": "forge:and",
          "values": [
            {
              "type": "forge:item_exists",
              "item": "miners_delight:vegan_hamburger"
            },
            {
              "type": "forge:tag_empty",
              "tag": "some_assembly_required:burger_bun"
            },
            {
              "type": "forge:mod_loaded",
              "modid": "miners_delight"
            }
          ]
        }
      ],
      "recipe": {
        "type": "minecraft:crafting_shapeless",
        "category": "misc",
        "ingredients": [
          {
            "tag": "forge:bread"
          },
          {
            "item": "miners_delight:vegan_patty"
          },
          {
            "tag": "forge:salad_ingredients"
          },
          {
            "tag": "forge:vegetables/tomato"
          },
          {
            "tag": "forge:vegetables/onion"
          }
        ],
        "result": {
          "item": "miners_delight:vegan_hamburger"
        }
      }
    }
  ]
}