{
  "type": "forge:conditional",
  "recipes": [
    {
      "conditions": [
        {
          "type": "forge:not",
          "value": {
            "type": "forge:tag_empty",
            "tag": "delightful:makes_dye/orange"
          }
        }
      ],
      "recipe": {
        "type": "farmersdelight:cutting",
        "ingredients": [
          {
            "tag": "delightful:makes_dye/orange"
          }
        ],
        "result": [
          {
            "count": 2,
            "item": "minecraft:orange_dye"
          }
        ],
        "tool": {
          "tag": "forge:tools/knives"
        }
      }
    }
  ]
}